planner/__init__.py
planner/main.py
planner/planner.py
planner/planner_cli.py
termplanner/__init__.py
termplanner/main.py
termplanner/planner.py
termplanner/planner_cli.py
termplanner-1.0.0.dist-info/DESCRIPTION.rst
termplanner-1.0.0.dist-info/METADATA
termplanner-1.0.0.dist-info/RECORD
termplanner-1.0.0.dist-info/WHEEL
termplanner-1.0.0.dist-info/entry_points.txt
termplanner-1.0.0.dist-info/metadata.json
termplanner-1.0.0.dist-info/top_level.txt
tests/__init__.py
tests/test_planner.py
