Metadata-Version: 2.0
Name: termplanner
Version: 1.0.0
Summary: A simple command line application to plan your day.
Home-page: http://github.com/ModoUnreal/TermPlanner
Author: Alex Hurtado
Author-email: modounreal@gmail.com
License: MIT
Platform: UNKNOWN
Classifier: Development Status :: 4 - Beta
Classifier: Intended Audience :: Developers
Classifier: Natural Language :: English
Classifier: License :: OSI Approved :: MIT License
Classifier: Programming Language :: Python
Classifier: Programming Language :: Python :: 3
Requires-Dist: Click
